CHANGES.txt
LICENSE.txt
MANIFEST.in
README.txt
setup.py
js/__init__.py
js.jquery_qunit.egg-info/PKG-INFO
js.jquery_qunit.egg-info/SOURCES.txt
js.jquery_qunit.egg-info/dependency_links.txt
js.jquery_qunit.egg-info/entry_points.txt
js.jquery_qunit.egg-info/namespace_packages.txt
js.jquery_qunit.egg-info/not-zip-safe
js.jquery_qunit.egg-info/requires.txt
js.jquery_qunit.egg-info/top_level.txt
js/jquery_qunit/__init__.py
js/jquery_qunit/test_jquery_qunit.txt
js/jquery_qunit/resources/README.txt
js/jquery_qunit/resources/qunit.css
js/jquery_qunit/resources/qunit.js