Metadata-Version: 1.0
Name: js.jquery-qunit
Version: 0.5
Summary: Fanstatic packaging of jQuery QUnit
Home-page: UNKNOWN
Author: Fanstatic Developers
Author-email: fanstatic@googlegroups.com
License: BSD
Platform: UNKNOWN
